{
  "source": "user-provided impact rankings",
  "generatedAt": "2026-06-27T00:37:25.227Z",
  "blendMaxRaw": 2,
  "rankedCount": 173,
  "poolMatchedCount": 172,
  "ranks": {
    "jokicni01": 1,
    "gilgesh01": 2,
    "wembavi01": 3,
    "doncilu01": 4,
    "antetgi01": 5,
    "brunsja01": 6,
    "edwaran01": 7,
    "leonaka01": 8,
    "curryst01": 9,
    "cunnica01": 10,
    "tatumja01": 11,
    "mitchdo01": 12,
    "halibty01": 13,
    "duranke01": 14,
    "brownja02": 15,
    "jamesle01": 16,
    "maxeyty01": 17,
    "townska01": 18,
    "davisan02": 19,
    "bookede01": 20,
    "barnesc01": 21,
    "johnsja05": 22,
    "siakapa01": 23,
    "butleji01": 24,
    "murraja01": 25,
    "embiijo01": 26,
    "avdijde01": 27,
    "adebaba01": 28,
    "anunoog01": 29,
    "mobleev01": 30,
    "hardeja01": 31,
    "jacksja02": 32,
    "irvinky01": 33,
    "sengual01": 34,
    "wagnefr01": 35,
    "banchpa01": 36,
    "willija06": 37,
    "ballla01": 38,
    "youngtr01": 39,
    "holmgch01": 40,
    "markkla01": 41,
    "castlst01": 42,
    "foxde01": 43,
    "lillada01": 44,
    "reaveau01": 45,
    "willizi01": 46,
    "murphtr02": 47,
    "portemi01": 48,
    "whitede01": 49,
    "gordoaa01": 50,
    "goberru01": 51,
    "powelno01": 52,
    "alexani01": 53,
    "flaggco01": 54,
    "randlju01": 55,
    "mcdanja02": 56,
    "banede01": 57,
    "durenja01": 58,
    "ingrabr01": 59,
    "knuepko01": 60,
    "herroty01": 61,
    "harpedy01": 62,
    "garlada01": 63,
    "bridgmi01": 64,
    "mccolcj01": 65,
    "thompam01": 66,
    "allenja01": 67,
    "georgke01": 68,
    "millebr02": 69,
    "brookdi01": 70,
    "carusal01": 71,
    "moranja01": 72,
    "lavinza01": 73,
    "hartjo01": 74,
    "porzikr01": 75,
    "vassede01": 76,
    "zubaciv01": 77,
    "thompau01": 78,
    "turnemy01": 79,
    "georgpa01": 80,
    "holidjr01": 81,
    "whiteco01": 82,
    "dosunay01": 83,
    "sabondo01": 84,
    "reidna01": 85,
    "pritcpa01": 86,
    "edgecvj01": 87,
    "okongon01": 88,
    "barrerj01": 89,
    "jaqueja01": 90,
    "giddejo01": 91,
    "harteis01": 92,
    "mitchaj01": 93,
    "nembhan01": 94,
    "dortlu01": 95,
    "camarto01": 96,
    "daniedy01": 97,
    "wallaca01": 98,
    "suggsja01": 99,
    "bridgmi02": 100,
    "sextoco01": 101,
    "clingdo01": 102,
    "greenja05": 103,
    "harrito02": 104,
    "derozde01": 105,
    "claxtni01": 106,
    "quickim01": 107,
    "murrade01": 108,
    "rolliry01": 109,
    "greendr01": 110,
    "champju02": 111,
    "johnsca02": 112,
    "johnske04": 113,
    "wiggian01": 114,
    "hachiru01": 115,
    "collijo01": 116,
    "vanvlfr01": 117,
    "huntede01": 118,
    "buzelma01": 119,
    "iveyja01": 120,
    "mathube01": 121,
    "aytonde01": 122,
    "sharpsh01": 123,
    "simonan01": 124,
    "grimequ01": 125,
    "mccaija01": 126,
    "monkma01": 127,
    "livelde01": 128,
    "washipj01": 129,
    "smithja05": 130,
    "sarral01": 131,
    "grantje01": 132,
    "murraco01": 133,
    "georgky01": 134,
    "westbru01": 135,
    "porteke02": 136,
    "easonta01": 137,
    "marshna01": 138,
    "oubreke01": 139,
    "blackan01": 140,
    "sensabr01": 141,
    "jeromty01": 142,
    "poeltja01": 143,
    "baileac01": 144,
    "murrake02": 145,
    "hendesc01": 146,
    "kesslwa01": 147,
    "cowarce01": 148,
    "nesmiaa01": 149,
    "kuzmaky01": 150,
    "watsope01": 151,
    "fearsje01": 152,
    "beysa01": 153,
    "hardati02": 154,
    "middlkh01": 155,
    "poolejo01": 156,
    "sheppre01": 157,
    "gilleco01": 158,
    "wellsja01": 159,
    "merrisa01": 160,
    "podzibr01": 161,
    "jonestr01": 162,
    "meltode01": 163,
    "chrisma02": 164,
    "vucevni01": 165,
    "thompkl01": 166,
    "willima07": 167,
    "strusma01": 168,
    "wareke01": 169,
    "braunch01": 170,
    "coulibi01": 171,
    "joeis01": 172,
    "wiggiaa01": 173
  },
  "adjustments": {
    "jokicni01": 0.004,
    "gilgesh01": 0,
    "wembavi01": -0.008,
    "doncilu01": 0.175,
    "antetgi01": 0.01,
    "brunsja01": 0.788,
    "edwaran01": 0.02,
    "leonaka01": -0.014,
    "curryst01": 0.109,
    "cunnica01": 0.094,
    "tatumja01": 0.622,
    "mitchdo01": 0.318,
    "halibty01": -0.095,
    "duranke01": -0.11,
    "brownja02": 0.399,
    "jamesle01": 0.054,
    "maxeyty01": 0.106,
    "townska01": -0.067,
    "davisan02": 0.124,
    "bookede01": 0.723,
    "barnesc01": -0.15,
    "johnsja05": -0.121,
    "siakapa01": 0.553,
    "butleji01": -0.181,
    "murraja01": -0.103,
    "embiijo01": -0.073,
    "avdijde01": 0.17,
    "adebaba01": 0.529,
    "anunoog01": -0.187,
    "mobleev01": -0.165,
    "hardeja01": -0.105,
    "jacksja02": -0.241,
    "irvinky01": 0.059,
    "sengual01": 0.002,
    "wagnefr01": 0.249,
    "banchpa01": 0.252,
    "willija06": 0.413,
    "ballla01": 0.502,
    "youngtr01": 0.303,
    "holmgch01": -0.431,
    "markkla01": 0.235,
    "castlst01": -0.151,
    "foxde01": 0.081,
    "lillada01": -0.144,
    "reaveau01": -0.384,
    "willizi01": -0.01,
    "murphtr02": -0.041,
    "portemi01": 0.173,
    "whitede01": -0.097,
    "gordoaa01": -0.229,
    "goberru01": -0.563,
    "powelno01": -0.095,
    "alexani01": -0.414,
    "flaggco01": 0.155,
    "randlju01": 0.282,
    "mcdanja02": -0.471,
    "banede01": -0.411,
    "durenja01": -0.558,
    "ingrabr01": -0.135,
    "knuepko01": -0.439,
    "herroty01": -0.016,
    "harpedy01": -0.125,
    "garlada01": -0.047,
    "bridgmi01": -0.208,
    "mccolcj01": 0.424,
    "thompam01": -0.449,
    "allenja01": -0.689,
    "georgke01": -0.206,
    "millebr02": -0.352,
    "brookdi01": 0.149,
    "carusal01": 0.321,
    "moranja01": 0.485,
    "lavinza01": -0.238,
    "hartjo01": -0.736,
    "porzikr01": -0.606,
    "vassede01": -0.052,
    "zubaciv01": -0.416,
    "thompau01": -0.079,
    "turnemy01": -0.772,
    "georgpa01": -0.391,
    "holidjr01": -0.586,
    "whiteco01": 0.163,
    "dosunay01": -0.807,
    "sabondo01": 0.057,
    "reidna01": -0.598,
    "pritcpa01": -0.089,
    "edgecvj01": 0.213,
    "okongon01": -0.716,
    "barrerj01": 0.025,
    "jaqueja01": -0.158,
    "giddejo01": -0.709,
    "harteis01": -0.837,
    "mitchaj01": -0.182,
    "nembhan01": -0.535,
    "dortlu01": -0.325,
    "camarto01": -0.842,
    "daniedy01": -0.266,
    "wallaca01": -0.094,
    "suggsja01": -0.503,
    "bridgmi02": 0.051,
    "sextoco01": -0.537,
    "clingdo01": -1.073,
    "greenja05": 0.263,
    "harrito02": -0.782,
    "derozde01": -0.059,
    "claxtni01": -0.816,
    "quickim01": -0.326,
    "murrade01": -0.637,
    "rolliry01": -0.75,
    "greendr01": -0.2,
    "champju02": -1.009,
    "johnsca02": -0.939,
    "johnske04": -0.707,
    "wiggian01": -0.85,
    "hachiru01": -0.839,
    "collijo01": -1.142,
    "vanvlfr01": -0.248,
    "huntede01": 0.044,
    "buzelma01": -0.705,
    "mathube01": -0.096,
    "aytonde01": -1.089,
    "sharpsh01": 0.008,
    "simonan01": -0.247,
    "grimequ01": -0.577,
    "mccaija01": 0.011,
    "monkma01": -0.293,
    "livelde01": -1.117,
    "washipj01": -0.664,
    "smithja05": -0.991,
    "sarral01": -0.785,
    "grantje01": -0.991,
    "murraco01": -1.284,
    "georgky01": -0.576,
    "westbru01": -0.176,
    "porteke02": -1.199,
    "easonta01": -0.724,
    "marshna01": -0.889,
    "oubreke01": -0.511,
    "blackan01": -0.504,
    "sensabr01": -0.531,
    "jeromty01": -1.291,
    "poeltja01": -1.602,
    "baileac01": -0.408,
    "murrake02": -1.064,
    "hendesc01": -0.285,
    "kesslwa01": -1.638,
    "cowarce01": -0.653,
    "nesmiaa01": -1.009,
    "kuzmaky01": -0.572,
    "watsope01": -1.508,
    "fearsje01": -0.265,
    "beysa01": -0.659,
    "hardati02": -1.199,
    "middlkh01": -0.379,
    "poolejo01": -0.166,
    "sheppre01": -1.424,
    "gilleco01": -1.249,
    "wellsja01": -1.009,
    "merrisa01": -1.482,
    "podzibr01": -1.07,
    "jonestr01": -1.183,
    "meltode01": -0.52,
    "chrisma02": -1.131,
    "vucevni01": -1.267,
    "thompkl01": -0.443,
    "willima07": -1.833,
    "strusma01": -1.208,
    "wareke01": -1.916,
    "braunch01": -1.643,
    "coulibi01": -0.834,
    "joeis01": -1.827,
    "wiggiaa01": -1.075
  }
}
